setup.py
test_pkg/__init__.py
test_pkg.egg-info/PKG-INFO
test_pkg.egg-info/SOURCES.txt
test_pkg.egg-info/dependency_links.txt
test_pkg.egg-info/not-zip-safe
test_pkg.egg-info/top_level.txt