Metadata-Version: 1.0
Name: test-pkg
Version: 0.1
Summary: The funniest joke in the world
Home-page: https://github.com/IanNMarshall/test_pkg/
Author: IanNMarshall
Author-email: ian.nicholas.marshall@gmail.com
License: UNKNOWN
Platform: UNKNOWN
